MANIFEST.in
README.md
cggtag.c
ggtag.py
setup.py
ggtag.egg-info/PKG-INFO
ggtag.egg-info/SOURCES.txt
ggtag.egg-info/dependency_links.txt
ggtag.egg-info/top_level.txt
host/include/ggtag.h
host/include/utils.h
host/src/ggtag.cpp
host/src/rfid.cpp
host/src/utils.cpp
shared/include/GUI_Paint.h
shared/include/debug.h
shared/include/fonts.h
shared/include/protocol.h
shared/include/qrcodegen.h
shared/include/rfid.h
shared/include/stb_truetype.h
shared/src/GUI_Paint.c
shared/src/courier.c
shared/src/debug.c
shared/src/fa.c
shared/src/font12.c
shared/src/font16.c
shared/src/font20.c
shared/src/font24.c
shared/src/font28.c
shared/src/font32.c
shared/src/font36.c
shared/src/font8.c
shared/src/protocol.cpp
shared/src/qrcodegen.c