Metadata-Version: 2.1
Name: ggtag
Version: 1.1.0
Summary: Python bindings for ggtag
Home-page: https://github.com/rgerganov/ggtag
Author: Radoslav Gerganov
Author-email: rgerganov@gmail.com
License: UNKNOWN
Platform: UNKNOWN
